jarvis_nifti/__init__.py
jarvis_nifti/main.py
jarvis_md_nifti-0.0.1a1.dist-info/METADATA
jarvis_md_nifti-0.0.1a1.dist-info/WHEEL
jarvis_md_nifti-0.0.1a1.dist-info/entry_points.txt
jarvis_md_nifti-0.0.1a1.dist-info/top_level.txt
jarvis_md_nifti-0.0.1a1.dist-info/RECORD
